meshset/__init__.py
meshset/_ball.py
meshset/_cube.py
meshset/_disk.py
meshset/_helpers.py
meshset/_moebius.py
meshset/_ngon.py
meshset/_rectangle.py
meshset/_sphere.py
meshset/_triangle.py
meshset/_tube.py
meshset-0.9.0.dist-info/LICENSE
meshset-0.9.0.dist-info/METADATA
meshset-0.9.0.dist-info/WHEEL
meshset-0.9.0.dist-info/top_level.txt
meshset-0.9.0.dist-info/RECORD
