Metadata-Version: 2.1
Name: meshset
Version: 0.9.0
Summary: The Python package for classic domain mesh generation.
Home-page: https://github.com/jasonmulderrig/meshset
Author: Jason Mulderrig
Author-email: jpm445@cornell.edu
Maintainer: Jason Mulderrig
Maintainer-email: jpm445@cornell.edu, mulderrig.jason@gmail.com
License: GNU General Public License v3 or later (GPLv3+)
Keywords: mesh
Classifier: Development Status :: 3 - Alpha
Classifier: Intended Audience :: Science/Research
Classifier: License :: OSI Approved :: GNU General Public License v3 or later (GPLv3+)
Classifier: Natural Language :: English
Classifier: Operating System :: Unix
Classifier: Programming Language :: Python :: 3.7
Classifier: Programming Language :: Python :: 3.8
Classifier: Programming Language :: Python :: 3.9
Classifier: Programming Language :: Python :: 3.10
Classifier: Topic :: Scientific/Engineering
Requires-Python: <4,>=3.7
License-File: LICENSE
Requires-Dist: numpy (>=1.21.5)
Requires-Dist: matplotlib (>=3.5.1)
